ufazien/__init__.py
ufazien/cli.py
ufazien/client.py
ufazien/project.py
ufazien/utils.py
ufazien/commands/__init__.py
ufazien_cli-0.3.0.dist-info/METADATA
ufazien_cli-0.3.0.dist-info/WHEEL
ufazien_cli-0.3.0.dist-info/entry_points.txt
ufazien_cli-0.3.0.dist-info/top_level.txt
ufazien_cli-0.3.0.dist-info/RECORD
