Metadata-Version: 2.4
Name: ufazien-cli
Version: 0.3.0
Summary: Command-line interface for deploying web applications on Ufazien platform
Author-email: Ufazien <ufazien@gmail.com>
License: MIT
Project-URL: Homepage, https://ufazien.com
Project-URL: Documentation, https://howtohoston.ufazien.com
Project-URL: Repository, https://github.com/martian56/ufazien-cli
Project-URL: Issues, https://github.com/martian56/ufazien-cli/issues
Keywords: ufazien,cli,deployment,hosting,web
Classifier: Development Status :: 4 - Beta
Classifier: Intended Audience :: Developers
Classifier: License :: OSI Approved :: MIT License
Classifier: Programming Language :: Python :: 3
Classifier: Programming Language :: Python :: 3.8
Classifier: Programming Language :: Python :: 3.9
Classifier: Programming Language :: Python :: 3.10
Classifier: Programming Language :: Python :: 3.11
Classifier: Programming Language :: Python :: 3.12
Classifier: Topic :: Software Development :: Libraries :: Python Modules
Classifier: Topic :: Internet :: WWW/HTTP
Requires-Python: >=3.8
Requires-Dist: typer>=0.9.0
Requires-Dist: rich>=13.0.0
Requires-Dist: requests>=2.31.0
Provides-Extra: dev
Requires-Dist: pytest>=7.0.0; extra == "dev"
Requires-Dist: pytest-cov>=4.0.0; extra == "dev"
Requires-Dist: black>=23.0.0; extra == "dev"
Requires-Dist: ruff>=0.1.0; extra == "dev"
Requires-Dist: mypy>=1.0.0; extra == "dev"
